<?xml version="1.0" encoding="UTF-8"?>
<!DOCTYPE filesystem PUBLIC "-//NetBeans//DTD Filesystem 1.1//EN" "http://www.netbeans.org/dtds/filesystem-1_1.dtd">
<filesystem>
    <folder name="Toolbars">
        <file name="Build_hidden"/>
        <file name="Clipboard_hidden"/>
        <file name="Edit_hidden"/>
        <file name="QuickSearch_hidden"/>
        <file name="UndoRedo_hidden"/>
    </folder>
    <folder name="Menu">
        <file name="BuildProject_hidden"/>
        <file name="Edit_hidden"/>
        <folder name="File">
            <file name="Separator2.instance_hidden"/>
            <file name="Separator3.instance_hidden"/>
            <file name="org-openide-actions-PageSetupAction.instance_hidden"/>
            <file name="org-openide-actions-PrintAction.instance_hidden"/>
            <file name="org-openide-actions-SaveAsAction.shadow_hidden"/>
        </folder>
        <folder name="GoTo">
            <file name="SeparatorBeforeGoToLine.instance_hidden"/>
            <file name="core-windows-SeparatorAfterRecentList.instance_hidden"/>
            <file name="org-netbeans-modules-favorites-SelectInFavorites.shadow_hidden"/>
            <file name="org-openide-actions-GotoAction.shadow_hidden"/>
        </folder>
        <file name="Refactoring_hidden"/>
        <file name="RunProject_hidden"/>
        <file name="Source_hidden"/>
        <folder name="Tools">
            <file name="Separator1.instance_hidden"/>
            <file name="Separator2.instance_hidden"/>
            <file name="org-netbeans-modules-favorites-templates-TemplatesAction.instance_hidden"/>
            <file name="org-openide-actions-ToolsAction.instance_hidden"/>
        </folder>
        <folder name="Window">
            <file name="Output_hidden"/>
            <file name="SwitchToRecentDocumentAction.shadow_hidden"/>
            <file name="ViewRuntimeTabAction.shadow_hidden"/>
            <file name="org-netbeans-core-actions-GlobalPropertiesAction.shadow_hidden"/>
        </folder>
    </folder>
     <folder name="Windows2">
        <folder name="Components">
            <file name="favorites.settings_hidden"/>
            <file name="output.settings_hidden"/>
            <file name="runtime.settings_hidden"/>
        </folder>
         <folder name="Modes">
            <folder name="navigator">
                <file name="navigatorTC.wstcref_hidden"/>
            </folder>
        </folder>
    </folder>
</filesystem>
